README
hgticket.py
setup.py
hgticket.egg-info/PKG-INFO
hgticket.egg-info/SOURCES.txt
hgticket.egg-info/dependency_links.txt
hgticket.egg-info/top_level.txt
hgticket.egg-info/zip-safe