Metadata-Version: 1.1
Name: hgticket
Version: 1.0
Summary: **Mercurial extension to detect JIRA-style ticket number in a commit message**
Home-page: http://bitbucket.org/adimian/hgticket
Author: Eric Gazoni
Author-email: eric.gazoni@adimian.com
License: MIT
Download-URL: http://bitbucket.org/adimian/hgticket/downloads
Keywords: mercurial hg scm jira ticket
Platform: UNKNOWN
